flinter/__init__.py
flinter/_cli_utils.py
flinter/_lizard.py
flinter/cli.py
flinter/io.py
flinter/nesting_utils.py
flinter/nobvisual.py
flinter/post_processing.py
flinter/rules.py
flinter/scan.py
flinter/utils.py
flinter/default_rules/cpp_rc_default.yml
flinter/default_rules/fortran_rc_default.yml
flinter/default_rules/python_rc_default.yml
flinter/error_processing/__init__.py
flinter/error_processing/_regexp.py
flinter/error_processing/_struct.py
flinter-0.7.1.dist-info/LICENSE
flinter-0.7.1.dist-info/METADATA
flinter-0.7.1.dist-info/WHEEL
flinter-0.7.1.dist-info/entry_points.txt
flinter-0.7.1.dist-info/top_level.txt
flinter-0.7.1.dist-info/RECORD
