Metadata-Version: 2.1
Name: flinter
Version: 0.7.1
Summary: Flinter, a multi-language code linter.
Home-page: https://gitlab.com/cerfacs/flint
Author: CoopTeam-CERFACS
Author-email: coop@cerfacs.com
License: UNKNOWN
Project-URL: Homepage, https://gitlab.com/cerfacs/flint
Project-URL: Documentation, https://flinter.readthedocs.io/en/latest/
Project-URL: Bug Tracker, https://gitlab.com/cerfacs/flint/-/issues
Keywords: linter,fortran,circular packing,code metrics,code analysis
Platform: UNKNOWN
Classifier: Programming Language :: Python :: 3.7
Classifier: Programming Language :: Python :: 3.8
Classifier: Programming Language :: Python :: 3.9
Classifier: Programming Language :: Python :: 3.10
Classifier: License :: CeCILL-B Free Software License Agreement (CECILL-B)
Requires-Python: >=3.7
Requires-Dist: click
Requires-Dist: lizard
Requires-Dist: pyyaml
Requires-Dist: nobvisual (>=0.3.0)
Requires-Dist: prettytable
Provides-Extra: docs
Requires-Dist: myst-parser ; extra == 'docs'
Requires-Dist: sphinx-rtd-theme ; extra == 'docs'
Provides-Extra: tests
Requires-Dist: pytest ; extra == 'tests'
